[{"id":"PSE1","category":"state","display_name":"高揚","description":"description"},{"id":"PSE2","category":"state","display_name":"角力","description":"description"},{"id":"PSE3","category":"state","display_name":"回流","description":"description"},{"id":"PSE4","category":"state","display_name":"擴流","description":"description"},{"id":"PSE5","category":"state","display_name":"破流","description":"description"},{"id":"PSE6","category":"state","display_name":"負荷流轉","description":"description"},{"id":"PSE7","category":"state","display_name":"負荷流轉2","description":"description"},{"id":"PSE8","category":"state","display_name":"節流","description":"description"},{"id":"PSE9","category":"state","display_name":"游刃","description":"description"},{"id":"PSE10","category":"state","display_name":"以太壓制","description":"description"},{"id":"PSE11","category":"state","display_name":"以太壓制2","description":"description"},{"id":"PSE12","category":"state","display_name":"逆風","description":"description"},{"id":"PSS1","category":"stress","display_name":"解壓","description":"description"},{"id":"PSS2","category":"stress","display_name":"追風","description":"description"},{"id":"PSS3","category":"stress","display_name":"化勁","description":"description"},{"id":"PSS4","category":"stress","display_name":"積壓","description":"description"},{"id":"PSS5","category":"stress","display_name":"積效","description":"description"},{"id":"PSS6","category":"stress","display_name":"變頻","description":"description"},{"id":"PSS7","category":"stress","display_name":"借風","description":"description"},{"id":"PSS8","category":"stress","display_name":"借力","description":"description"},{"id":"PSS9","category":"stress","display_name":"行雲流水","description":"description"},{"id":"PSS10","category":"stress","display_name":"負荷壓制","description":"description"},{"id":"PSS11","category":"stress","display_name":"負荷壓制2","description":"description"},{"id":"PSS12","category":"stress","display_name":"逆轉","description":"description"},{"id":"PSL1","category":"life","display_name":"活性","description":"description"},{"id":"PSL2","category":"life","display_name":"激昂","description":"description"},{"id":"PSL3","category":"life","display_name":"猛烈","description":"description"},{"id":"PSL4","category":"life","display_name":"堅韌","description":"description"},{"id":"PSL5","category":"life","display_name":"循環力","description":"description"},{"id":"PSL6","category":"life","display_name":"能量循環","description":"description"},{"id":"PSL7","category":"life","display_name":"負荷循環","description":"description"},{"id":"PSL8","category":"life","display_name":"逆境流轉","description":"description"},{"id":"PSL9","category":"life","display_name":"生命壓制","description":"description"},{"id":"PSL10","category":"life","display_name":"生命壓制2","description":"description"},{"id":"PSL11","category":"life","display_name":"逆流而上","description":"description"},{"id":"PSL12","category":"life","display_name":"生生不息","description":"description"}]